[{"jurisdiccion_codigo_indec":"02","jurisdiccion_nombre":"CABA","vacuna_nombre":"AstraZeneca ChAdOx1 S recombinante","primera_dosis_cantidad":2421751,"segunda_dosis_cantidad":2060225,"vacunas":[{"vacuna_nombre":"AstraZeneca ChAdOx1 S recombinante","primera_dosis_cantidad":"673574","segunda_dosis_cantidad":"685082"},{"vacuna_nombre":"COVISHIELD ChAdOx1nCoV COVID 19","primera_dosis_cantidad":"65224","segunda_dosis_cantidad":"183"},{"vacuna_nombre":"Cansino Ad5 nCoV","primera_dosis_cantidad":"25722","segunda_dosis_cantidad":"0"},{"vacuna_nombre":"Moderna ARNm","primera_dosis_cantidad":"19210","segunda_dosis_cantidad":"243635"},{"vacuna_nombre":"Pfizer BioNTech Comirnaty","primera_dosis_cantidad":"63208","segunda_dosis_cantidad":"14863"},{"vacuna_nombre":"Sinopharm Vacuna SARSCOV 2 inactivada","primera_dosis_cantidad":"685748","segunda_dosis_cantidad":"625013"},{"vacuna_nombre":"Sputnik V COVID19 Instituto Gamaleya","primera_dosis_cantidad":"889065","segunda_dosis_cantidad":"491449"}]},{"jurisdiccion_codigo_indec":"06","jurisdiccion_nombre":"Buenos Aires","vacuna_nombre":"AstraZeneca ChAdOx1 S recombinante","primera_dosis_cantidad":11959358,"segunda_dosis_cantidad":9611194,"vacunas":[{"vacuna_nombre":"AstraZeneca ChAdOx1 S recombinante","primera_dosis_cantidad":"3394514","segunda_dosis_cantidad":"3603191"},{"vacuna_nombre":"COVISHIELD ChAdOx1nCoV COVID 19","primera_dosis_cantidad":"251009","segunda_dosis_cantidad":"323"},{"vacuna_nombre":"Cansino Ad5 nCoV","primera_dosis_cantidad":"13723","segunda_dosis_cantidad":"0"},{"vacuna_nombre":"Moderna ARNm","primera_dosis_cantidad":"300735","segunda_dosis_cantidad":"906770"},{"vacuna_nombre":"Pfizer BioNTech Comirnaty","primera_dosis_cantidad":"169470","segunda_dosis_cantidad":"0"},{"vacuna_nombre":"Sinopharm Vacuna SARSCOV 2 inactivada","primera_dosis_cantidad":"3797479","segunda_dosis_cantidad":"2992668"},{"vacuna_nombre":"Sputnik V COVID19 Instituto Gamaleya","primera_dosis_cantidad":"4032428","segunda_dosis_cantidad":"2108242"}]},{"jurisdiccion_codigo_indec":"94","jurisdiccion_nombre":"Tierra del Fuego","vacuna_nombre":"AstraZeneca ChAdOx1 S recombinante","primera_dosis_cantidad":122654,"segunda_dosis_cantidad":99538,"vacunas":[{"vacuna_nombre":"AstraZeneca ChAdOx1 S recombinante","primera_dosis_cantidad":"32291","segunda_dosis_cantidad":"31895"},{"vacuna_nombre":"COVISHIELD ChAdOx1nCoV COVID 19","primera_dosis_cantidad":"2726","segunda_dosis_cantidad":"750"},{"vacuna_nombre":"Moderna ARNm","primera_dosis_cantidad":"1754","segunda_dosis_cantidad":"10730"},{"vacuna_nombre":"Pfizer BioNTech Comirnaty","primera_dosis_cantidad":"4374","segunda_dosis_cantidad":"24"},{"vacuna_nombre":"Sinopharm Vacuna SARSCOV 2 inactivada","primera_dosis_cantidad":"38025","segunda_dosis_cantidad":"31872"},{"vacuna_nombre":"Sputnik V COVID19 Instituto Gamaleya","primera_dosis_cantidad":"43484","segunda_dosis_cantidad":"24267"}]},{"jurisdiccion_codigo_indec":"90","jurisdiccion_nombre":"Tucumán","vacuna_nombre":"AstraZeneca ChAdOx1 S recombinante","primera_dosis_cantidad":1087623,"segunda_dosis_cantidad":799049,"vacunas":[{"vacuna_nombre":"AstraZeneca ChAdOx1 S recombinante","primera_dosis_cantidad":"293402","segunda_dosis_cantidad":"273702"},{"vacuna_nombre":"COVISHIELD ChAdOx1nCoV COVID 19","primera_dosis_cantidad":"20536","segunda_dosis_cantidad":"57"},{"vacuna_nombre":"Moderna ARNm","primera_dosis_cantidad":"30414","segunda_dosis_cantidad":"72619"},{"vacuna_nombre":"Pfizer BioNTech Comirnaty","primera_dosis_cantidad":"26467","segunda_dosis_cantidad":"0"},{"vacuna_nombre":"Sinopharm Vacuna SARSCOV 2 inactivada","primera_dosis_cantidad":"323599","segunda_dosis_cantidad":"250904"},{"vacuna_nombre":"Sputnik V COVID19 Instituto Gamaleya","primera_dosis_cantidad":"393205","segunda_dosis_cantidad":"201767"}]},{"jurisdiccion_codigo_indec":"86","jurisdiccion_nombre":"Santiago del Estero","vacuna_nombre":"AstraZeneca ChAdOx1 S recombinante","primera_dosis_cantidad":704561,"segunda_dosis_cantidad":564638,"vacunas":[{"vacuna_nombre":"AstraZeneca ChAdOx1 S recombinante","primera_dosis_cantidad":"204224","segunda_dosis_cantidad":"187908"},{"vacuna_nombre":"COVISHIELD ChAdOx1nCoV COVID 19","primera_dosis_cantidad":"11848","segunda_dosis_cantidad":"1161"},{"vacuna_nombre":"Cansino Ad5 nCoV","primera_dosis_cantidad":"4718","segunda_dosis_cantidad":"0"},{"vacuna_nombre":"Moderna ARNm","primera_dosis_cantidad":"7143","segunda_dosis_cantidad":"61166"},{"vacuna_nombre":"Pfizer BioNTech Comirnaty","primera_dosis_cantidad":"19842","segunda_dosis_cantidad":"78"},{"vacuna_nombre":"Sinopharm Vacuna SARSCOV 2 inactivada","primera_dosis_cantidad":"240306","segunda_dosis_cantidad":"197980"},{"vacuna_nombre":"Sputnik V COVID19 Instituto Gamaleya","primera_dosis_cantidad":"216480","segunda_dosis_cantidad":"116345"}]},{"jurisdiccion_codigo_indec":"82","jurisdiccion_nombre":"Santa Fe","vacuna_nombre":"AstraZeneca ChAdOx1 S recombinante","primera_dosis_cantidad":2474640,"segunda_dosis_cantidad":2035685,"vacunas":[{"vacuna_nombre":"AstraZeneca ChAdOx1 S recombinante","primera_dosis_cantidad":"742937","segunda_dosis_cantidad":"704049"},{"vacuna_nombre":"COVISHIELD ChAdOx1nCoV COVID 19","primera_dosis_cantidad":"41233","segunda_dosis_cantidad":"52"},{"vacuna_nombre":"Cansino Ad5 nCoV","primera_dosis_cantidad":"5652","segunda_dosis_cantidad":"0"},{"vacuna_nombre":"Moderna ARNm","primera_dosis_cantidad":"29348","segunda_dosis_cantidad":"221944"},{"vacuna_nombre":"Pfizer BioNTech Comirnaty","primera_dosis_cantidad":"32032","segunda_dosis_cantidad":"8"},{"vacuna_nombre":"Sinopharm Vacuna SARSCOV 2 inactivada","primera_dosis_cantidad":"761466","segunda_dosis_cantidad":"656166"},{"vacuna_nombre":"Sputnik V COVID19 Instituto Gamaleya","primera_dosis_cantidad":"861972","segunda_dosis_cantidad":"453466"}]},{"jurisdiccion_codigo_indec":"78","jurisdiccion_nombre":"Santa Cruz","vacuna_nombre":"AstraZeneca ChAdOx1 S recombinante","primera_dosis_cantidad":223708,"segunda_dosis_cantidad":169617,"vacunas":[{"vacuna_nombre":"AstraZeneca ChAdOx1 S recombinante","primera_dosis_cantidad":"58924","segunda_dosis_cantidad":"52861"},{"vacuna_nombre":"COVISHIELD ChAdOx1nCoV COVID 19","primera_dosis_cantidad":"5912","segunda_dosis_cantidad":"713"},{"vacuna_nombre":"Cansino Ad5 nCoV","primera_dosis_cantidad":"1103","segunda_dosis_cantidad":"0"},{"vacuna_nombre":"Moderna ARNm","primera_dosis_cantidad":"8235","segunda_dosis_cantidad":"13259"},{"vacuna_nombre":"Pfizer BioNTech Comirnaty","primera_dosis_cantidad":"3998","segunda_dosis_cantidad":"56"},{"vacuna_nombre":"Sinopharm Vacuna SARSCOV 2 inactivada","primera_dosis_cantidad":"59732","segunda_dosis_cantidad":"50677"},{"vacuna_nombre":"Sputnik V COVID19 Instituto Gamaleya","primera_dosis_cantidad":"85804","segunda_dosis_cantidad":"52051"}]},{"jurisdiccion_codigo_indec":"74","jurisdiccion_nombre":"San Luis","vacuna_nombre":"AstraZeneca ChAdOx1 S recombinante","primera_dosis_cantidad":369099,"segunda_dosis_cantidad":307040,"vacunas":[{"vacuna_nombre":"AstraZeneca ChAdOx1 S recombinante","primera_dosis_cantidad":"97586","segunda_dosis_cantidad":"103567"},{"vacuna_nombre":"COVISHIELD ChAdOx1nCoV COVID 19","primera_dosis_cantidad":"6829","segunda_dosis_cantidad":"0"},{"vacuna_nombre":"Cansino Ad5 nCoV","primera_dosis_cantidad":"3948","segunda_dosis_cantidad":"0"},{"vacuna_nombre":"Moderna ARNm","primera_dosis_cantidad":"8756","segunda_dosis_cantidad":"27791"},{"vacuna_nombre":"Pfizer BioNTech Comirnaty","primera_dosis_cantidad":"10560","segunda_dosis_cantidad":"0"},{"vacuna_nombre":"Sinopharm Vacuna SARSCOV 2 inactivada","primera_dosis_cantidad":"121311","segunda_dosis_cantidad":"101717"},{"vacuna_nombre":"Sputnik V COVID19 Instituto Gamaleya","primera_dosis_cantidad":"120109","segunda_dosis_cantidad":"73965"}]},{"jurisdiccion_codigo_indec":"70","jurisdiccion_nombre":"San Juan","vacuna_nombre":"AstraZeneca ChAdOx1 S recombinante","primera_dosis_cantidad":525341,"segunda_dosis_cantidad":412641,"vacunas":[{"vacuna_nombre":"AstraZeneca ChAdOx1 S recombinante","primera_dosis_cantidad":"145508","segunda_dosis_cantidad":"144916"},{"vacuna_nombre":"COVISHIELD ChAdOx1nCoV COVID 19","primera_dosis_cantidad":"8811","segunda_dosis_cantidad":"12"},{"vacuna_nombre":"Cansino Ad5 nCoV","primera_dosis_cantidad":"72","segunda_dosis_cantidad":"0"},{"vacuna_nombre":"Moderna ARNm","primera_dosis_cantidad":"12779","segunda_dosis_cantidad":"36877"},{"vacuna_nombre":"Pfizer BioNTech Comirnaty","primera_dosis_cantidad":"11143","segunda_dosis_cantidad":"16"},{"vacuna_nombre":"Sinopharm Vacuna SARSCOV 2 inactivada","primera_dosis_cantidad":"155218","segunda_dosis_cantidad":"133670"},{"vacuna_nombre":"Sputnik V COVID19 Instituto Gamaleya","primera_dosis_cantidad":"191810","segunda_dosis_cantidad":"97150"}]},{"jurisdiccion_codigo_indec":"66","jurisdiccion_nombre":"Salta","vacuna_nombre":"AstraZeneca ChAdOx1 S recombinante","primera_dosis_cantidad":856553,"segunda_dosis_cantidad":586256,"vacunas":[{"vacuna_nombre":"AstraZeneca ChAdOx1 S recombinante","primera_dosis_cantidad":"297338","segunda_dosis_cantidad":"224127"},{"vacuna_nombre":"COVISHIELD ChAdOx1nCoV COVID 19","primera_dosis_cantidad":"17838","segunda_dosis_cantidad":"52"},{"vacuna_nombre":"Cansino Ad5 nCoV","primera_dosis_cantidad":"121","segunda_dosis_cantidad":"0"},{"vacuna_nombre":"Moderna ARNm","primera_dosis_cantidad":"18659","segunda_dosis_cantidad":"63439"},{"vacuna_nombre":"Pfizer BioNTech Comirnaty","primera_dosis_cantidad":"10861","segunda_dosis_cantidad":"371"},{"vacuna_nombre":"Sinopharm Vacuna SARSCOV 2 inactivada","primera_dosis_cantidad":"221540","segunda_dosis_cantidad":"139106"},{"vacuna_nombre":"Sputnik V COVID19 Instituto Gamaleya","primera_dosis_cantidad":"290196","segunda_dosis_cantidad":"159161"}]},{"jurisdiccion_codigo_indec":"62","jurisdiccion_nombre":"Río Negro","vacuna_nombre":"AstraZeneca ChAdOx1 S recombinante","primera_dosis_cantidad":533612,"segunda_dosis_cantidad":414777,"vacunas":[{"vacuna_nombre":"AstraZeneca ChAdOx1 S recombinante","primera_dosis_cantidad":"140715","segunda_dosis_cantidad":"136589"},{"vacuna_nombre":"COVISHIELD ChAdOx1nCoV COVID 19","primera_dosis_cantidad":"13964","segunda_dosis_cantidad":"89"},{"vacuna_nombre":"Cansino Ad5 nCoV","primera_dosis_cantidad":"1060","segunda_dosis_cantidad":"0"},{"vacuna_nombre":"Moderna ARNm","primera_dosis_cantidad":"8572","segunda_dosis_cantidad":"43300"},{"vacuna_nombre":"Pfizer BioNTech Comirnaty","primera_dosis_cantidad":"9757","segunda_dosis_cantidad":"21"},{"vacuna_nombre":"Sinopharm Vacuna SARSCOV 2 inactivada","primera_dosis_cantidad":"191302","segunda_dosis_cantidad":"146133"},{"vacuna_nombre":"Sputnik V COVID19 Instituto Gamaleya","primera_dosis_cantidad":"168242","segunda_dosis_cantidad":"88645"}]},{"jurisdiccion_codigo_indec":"58","jurisdiccion_nombre":"Neuquén","vacuna_nombre":"AstraZeneca ChAdOx1 S recombinante","primera_dosis_cantidad":478363,"segunda_dosis_cantidad":358363,"vacunas":[{"vacuna_nombre":"AstraZeneca ChAdOx1 S recombinante","primera_dosis_cantidad":"137341","segunda_dosis_cantidad":"118686"},{"vacuna_nombre":"COVISHIELD ChAdOx1nCoV COVID 19","primera_dosis_cantidad":"12770","segunda_dosis_cantidad":"58"},{"vacuna_nombre":"Cansino Ad5 nCoV","primera_dosis_cantidad":"4400","segunda_dosis_cantidad":"0"},{"vacuna_nombre":"Moderna ARNm","primera_dosis_cantidad":"11436","segunda_dosis_cantidad":"35426"},{"vacuna_nombre":"Pfizer BioNTech Comirnaty","primera_dosis_cantidad":"9167","segunda_dosis_cantidad":"3"},{"vacuna_nombre":"Sinopharm Vacuna SARSCOV 2 inactivada","primera_dosis_cantidad":"148499","segunda_dosis_cantidad":"117234"},{"vacuna_nombre":"Sputnik V COVID19 Instituto Gamaleya","primera_dosis_cantidad":"154750","segunda_dosis_cantidad":"86956"}]},{"jurisdiccion_codigo_indec":"54","jurisdiccion_nombre":"Misiones","vacuna_nombre":"AstraZeneca ChAdOx1 S recombinante","primera_dosis_cantidad":696389,"segunda_dosis_cantidad":477914,"vacunas":[{"vacuna_nombre":"AstraZeneca ChAdOx1 S recombinante","primera_dosis_cantidad":"208901","segunda_dosis_cantidad":"196108"},{"vacuna_nombre":"COVISHIELD ChAdOx1nCoV COVID 19","primera_dosis_cantidad":"16645","segunda_dosis_cantidad":"790"},{"vacuna_nombre":"Cansino Ad5 nCoV","primera_dosis_cantidad":"1932","segunda_dosis_cantidad":"0"},{"vacuna_nombre":"Moderna ARNm","primera_dosis_cantidad":"36575","segunda_dosis_cantidad":"43492"},{"vacuna_nombre":"Pfizer BioNTech Comirnaty","primera_dosis_cantidad":"8262","segunda_dosis_cantidad":"33"},{"vacuna_nombre":"Sinopharm Vacuna SARSCOV 2 inactivada","primera_dosis_cantidad":"191379","segunda_dosis_cantidad":"121048"},{"vacuna_nombre":"Sputnik V COVID19 Instituto Gamaleya","primera_dosis_cantidad":"232695","segunda_dosis_cantidad":"116443"}]},{"jurisdiccion_codigo_indec":"50","jurisdiccion_nombre":"Mendoza","vacuna_nombre":"AstraZeneca ChAdOx1 S recombinante","primera_dosis_cantidad":1288698,"segunda_dosis_cantidad":995282,"vacunas":[{"vacuna_nombre":"AstraZeneca ChAdOx1 S recombinante","primera_dosis_cantidad":"402085","segunda_dosis_cantidad":"352376"},{"vacuna_nombre":"COVISHIELD ChAdOx1nCoV COVID 19","primera_dosis_cantidad":"25216","segunda_dosis_cantidad":"407"},{"vacuna_nombre":"Cansino Ad5 nCoV","primera_dosis_cantidad":"2525","segunda_dosis_cantidad":"0"},{"vacuna_nombre":"Moderna ARNm","primera_dosis_cantidad":"22779","segunda_dosis_cantidad":"123298"},{"vacuna_nombre":"Pfizer BioNTech Comirnaty","primera_dosis_cantidad":"30483","segunda_dosis_cantidad":"181"},{"vacuna_nombre":"Sinopharm Vacuna SARSCOV 2 inactivada","primera_dosis_cantidad":"356069","segunda_dosis_cantidad":"280056"},{"vacuna_nombre":"Sputnik V COVID19 Instituto Gamaleya","primera_dosis_cantidad":"449541","segunda_dosis_cantidad":"238964"}]},{"jurisdiccion_codigo_indec":"46","jurisdiccion_nombre":"La Rioja","vacuna_nombre":"AstraZeneca ChAdOx1 S recombinante","primera_dosis_cantidad":283493,"segunda_dosis_cantidad":219828,"vacunas":[{"vacuna_nombre":"AstraZeneca ChAdOx1 S recombinante","primera_dosis_cantidad":"74998","segunda_dosis_cantidad":"69151"},{"vacuna_nombre":"COVISHIELD ChAdOx1nCoV COVID 19","primera_dosis_cantidad":"7204","segunda_dosis_cantidad":"108"},{"vacuna_nombre":"Cansino Ad5 nCoV","primera_dosis_cantidad":"1785","segunda_dosis_cantidad":"0"},{"vacuna_nombre":"Moderna ARNm","primera_dosis_cantidad":"8918","segunda_dosis_cantidad":"23279"},{"vacuna_nombre":"Pfizer BioNTech Comirnaty","primera_dosis_cantidad":"5101","segunda_dosis_cantidad":"58"},{"vacuna_nombre":"Sinopharm Vacuna SARSCOV 2 inactivada","primera_dosis_cantidad":"92933","segunda_dosis_cantidad":"72862"},{"vacuna_nombre":"Sputnik V COVID19 Instituto Gamaleya","primera_dosis_cantidad":"92554","segunda_dosis_cantidad":"54370"}]},{"jurisdiccion_codigo_indec":"42","jurisdiccion_nombre":"La Pampa","vacuna_nombre":"AstraZeneca ChAdOx1 S recombinante","primera_dosis_cantidad":272910,"segunda_dosis_cantidad":221200,"vacunas":[{"vacuna_nombre":"AstraZeneca ChAdOx1 S recombinante","primera_dosis_cantidad":"67170","segunda_dosis_cantidad":"72368"},{"vacuna_nombre":"COVISHIELD ChAdOx1nCoV COVID 19","primera_dosis_cantidad":"4572","segunda_dosis_cantidad":"0"},{"vacuna_nombre":"Cansino Ad5 nCoV","primera_dosis_cantidad":"2423","segunda_dosis_cantidad":"0"},{"vacuna_nombre":"Moderna ARNm","primera_dosis_cantidad":"4846","segunda_dosis_cantidad":"23957"},{"vacuna_nombre":"Pfizer BioNTech Comirnaty","primera_dosis_cantidad":"9620","segunda_dosis_cantidad":"219"},{"vacuna_nombre":"Sinopharm Vacuna SARSCOV 2 inactivada","primera_dosis_cantidad":"98082","segunda_dosis_cantidad":"77538"},{"vacuna_nombre":"Sputnik V COVID19 Instituto Gamaleya","primera_dosis_cantidad":"86197","segunda_dosis_cantidad":"47118"}]},{"jurisdiccion_codigo_indec":"38","jurisdiccion_nombre":"Jujuy","vacuna_nombre":"AstraZeneca ChAdOx1 S recombinante","primera_dosis_cantidad":525458,"segunda_dosis_cantidad":352887,"vacunas":[{"vacuna_nombre":"AstraZeneca ChAdOx1 S recombinante","primera_dosis_cantidad":"159994","segunda_dosis_cantidad":"125863"},{"vacuna_nombre":"COVISHIELD ChAdOx1nCoV COVID 19","primera_dosis_cantidad":"13972","segunda_dosis_cantidad":"286"},{"vacuna_nombre":"Cansino Ad5 nCoV","primera_dosis_cantidad":"25","segunda_dosis_cantidad":"0"},{"vacuna_nombre":"Moderna ARNm","primera_dosis_cantidad":"19937","segunda_dosis_cantidad":"20156"},{"vacuna_nombre":"Pfizer BioNTech Comirnaty","primera_dosis_cantidad":"6446","segunda_dosis_cantidad":"24"},{"vacuna_nombre":"Sinopharm Vacuna SARSCOV 2 inactivada","primera_dosis_cantidad":"172529","segunda_dosis_cantidad":"107786"},{"vacuna_nombre":"Sputnik V COVID19 Instituto Gamaleya","primera_dosis_cantidad":"152555","segunda_dosis_cantidad":"98772"}]},{"jurisdiccion_codigo_indec":"34","jurisdiccion_nombre":"Formosa","vacuna_nombre":"AstraZeneca ChAdOx1 S recombinante","primera_dosis_cantidad":455287,"segunda_dosis_cantidad":311843,"vacunas":[{"vacuna_nombre":"AstraZeneca ChAdOx1 S recombinante","primera_dosis_cantidad":"117379","segunda_dosis_cantidad":"123638"},{"vacuna_nombre":"COVISHIELD ChAdOx1nCoV COVID 19","primera_dosis_cantidad":"7347","segunda_dosis_cantidad":"1"},{"vacuna_nombre":"Cansino Ad5 nCoV","primera_dosis_cantidad":"247","segunda_dosis_cantidad":"0"},{"vacuna_nombre":"Moderna ARNm","primera_dosis_cantidad":"38761","segunda_dosis_cantidad":"4672"},{"vacuna_nombre":"Pfizer BioNTech Comirnaty","primera_dosis_cantidad":"6258","segunda_dosis_cantidad":"0"},{"vacuna_nombre":"Sinopharm Vacuna SARSCOV 2 inactivada","primera_dosis_cantidad":"154965","segunda_dosis_cantidad":"115016"},{"vacuna_nombre":"Sputnik V COVID19 Instituto Gamaleya","primera_dosis_cantidad":"130330","segunda_dosis_cantidad":"68516"}]},{"jurisdiccion_codigo_indec":"30","jurisdiccion_nombre":"Entre Ríos","vacuna_nombre":"AstraZeneca ChAdOx1 S recombinante","primera_dosis_cantidad":911195,"segunda_dosis_cantidad":669655,"vacunas":[{"vacuna_nombre":"AstraZeneca ChAdOx1 S recombinante","primera_dosis_cantidad":"271451","segunda_dosis_cantidad":"223595"},{"vacuna_nombre":"COVISHIELD ChAdOx1nCoV COVID 19","primera_dosis_cantidad":"17205","segunda_dosis_cantidad":"330"},{"vacuna_nombre":"Cansino Ad5 nCoV","primera_dosis_cantidad":"4355","segunda_dosis_cantidad":"0"},{"vacuna_nombre":"Moderna ARNm","primera_dosis_cantidad":"17540","segunda_dosis_cantidad":"64752"},{"vacuna_nombre":"Pfizer BioNTech Comirnaty","primera_dosis_cantidad":"6368","segunda_dosis_cantidad":"6"},{"vacuna_nombre":"Sinopharm Vacuna SARSCOV 2 inactivada","primera_dosis_cantidad":"294527","segunda_dosis_cantidad":"233360"},{"vacuna_nombre":"Sputnik V COVID19 Instituto Gamaleya","primera_dosis_cantidad":"299749","segunda_dosis_cantidad":"147612"}]},{"jurisdiccion_codigo_indec":"26","jurisdiccion_nombre":"Chubut","vacuna_nombre":"AstraZeneca ChAdOx1 S recombinante","primera_dosis_cantidad":391422,"segunda_dosis_cantidad":288463,"vacunas":[{"vacuna_nombre":"AstraZeneca ChAdOx1 S recombinante","primera_dosis_cantidad":"120469","segunda_dosis_cantidad":"107929"},{"vacuna_nombre":"COVISHIELD ChAdOx1nCoV COVID 19","primera_dosis_cantidad":"11741","segunda_dosis_cantidad":"615"},{"vacuna_nombre":"Cansino Ad5 nCoV","primera_dosis_cantidad":"43","segunda_dosis_cantidad":"0"},{"vacuna_nombre":"Moderna ARNm","primera_dosis_cantidad":"16471","segunda_dosis_cantidad":"23949"},{"vacuna_nombre":"Pfizer BioNTech Comirnaty","primera_dosis_cantidad":"4629","segunda_dosis_cantidad":"12"},{"vacuna_nombre":"Sinopharm Vacuna SARSCOV 2 inactivada","primera_dosis_cantidad":"106855","segunda_dosis_cantidad":"81073"},{"vacuna_nombre":"Sputnik V COVID19 Instituto Gamaleya","primera_dosis_cantidad":"131214","segunda_dosis_cantidad":"74885"}]},{"jurisdiccion_codigo_indec":"22","jurisdiccion_nombre":"Chaco","vacuna_nombre":"AstraZeneca ChAdOx1 S recombinante","primera_dosis_cantidad":736225,"segunda_dosis_cantidad":500676,"vacunas":[{"vacuna_nombre":"AstraZeneca ChAdOx1 S recombinante","primera_dosis_cantidad":"225823","segunda_dosis_cantidad":"174146"},{"vacuna_nombre":"COVISHIELD ChAdOx1nCoV COVID 19","primera_dosis_cantidad":"15356","segunda_dosis_cantidad":"601"},{"vacuna_nombre":"Cansino Ad5 nCoV","primera_dosis_cantidad":"323","segunda_dosis_cantidad":"0"},{"vacuna_nombre":"Moderna ARNm","primera_dosis_cantidad":"24126","segunda_dosis_cantidad":"48418"},{"vacuna_nombre":"Pfizer BioNTech Comirnaty","primera_dosis_cantidad":"6386","segunda_dosis_cantidad":"305"},{"vacuna_nombre":"Sinopharm Vacuna SARSCOV 2 inactivada","primera_dosis_cantidad":"224075","segunda_dosis_cantidad":"147449"},{"vacuna_nombre":"Sputnik V COVID19 Instituto Gamaleya","primera_dosis_cantidad":"240136","segunda_dosis_cantidad":"129757"}]},{"jurisdiccion_codigo_indec":"18","jurisdiccion_nombre":"Corrientes","vacuna_nombre":"AstraZeneca ChAdOx1 S recombinante","primera_dosis_cantidad":735771,"segunda_dosis_cantidad":475784,"vacunas":[{"vacuna_nombre":"AstraZeneca ChAdOx1 S recombinante","primera_dosis_cantidad":"174472","segunda_dosis_cantidad":"135250"},{"vacuna_nombre":"COVISHIELD ChAdOx1nCoV COVID 19","primera_dosis_cantidad":"19699","segunda_dosis_cantidad":"397"},{"vacuna_nombre":"Cansino Ad5 nCoV","primera_dosis_cantidad":"2767","segunda_dosis_cantidad":"0"},{"vacuna_nombre":"Moderna ARNm","primera_dosis_cantidad":"24400","segunda_dosis_cantidad":"49362"},{"vacuna_nombre":"Pfizer BioNTech Comirnaty","primera_dosis_cantidad":"7071","segunda_dosis_cantidad":"810"},{"vacuna_nombre":"Sinopharm Vacuna SARSCOV 2 inactivada","primera_dosis_cantidad":"260237","segunda_dosis_cantidad":"174329"},{"vacuna_nombre":"Sputnik V COVID19 Instituto Gamaleya","primera_dosis_cantidad":"247125","segunda_dosis_cantidad":"115636"}]},{"jurisdiccion_codigo_indec":"14","jurisdiccion_nombre":"Córdoba","vacuna_nombre":"AstraZeneca ChAdOx1 S recombinante","primera_dosis_cantidad":2591468,"segunda_dosis_cantidad":2110086,"vacunas":[{"vacuna_nombre":"AstraZeneca ChAdOx1 S recombinante","primera_dosis_cantidad":"765355","segunda_dosis_cantidad":"727594"},{"vacuna_nombre":"COVISHIELD ChAdOx1nCoV COVID 19","primera_dosis_cantidad":"43867","segunda_dosis_cantidad":"78"},{"vacuna_nombre":"Cansino Ad5 nCoV","primera_dosis_cantidad":"6311","segunda_dosis_cantidad":"0"},{"vacuna_nombre":"Moderna ARNm","primera_dosis_cantidad":"40762","segunda_dosis_cantidad":"229146"},{"vacuna_nombre":"Pfizer BioNTech Comirnaty","primera_dosis_cantidad":"33072","segunda_dosis_cantidad":"13"},{"vacuna_nombre":"Sinopharm Vacuna SARSCOV 2 inactivada","primera_dosis_cantidad":"825342","segunda_dosis_cantidad":"675941"},{"vacuna_nombre":"Sputnik V COVID19 Instituto Gamaleya","primera_dosis_cantidad":"876759","segunda_dosis_cantidad":"477314"}]},{"jurisdiccion_codigo_indec":"10","jurisdiccion_nombre":"Catamarca","vacuna_nombre":"AstraZeneca ChAdOx1 S recombinante","primera_dosis_cantidad":305260,"segunda_dosis_cantidad":226663,"vacunas":[{"vacuna_nombre":"AstraZeneca ChAdOx1 S recombinante","primera_dosis_cantidad":"84822","segunda_dosis_cantidad":"70695"},{"vacuna_nombre":"COVISHIELD ChAdOx1nCoV COVID 19","primera_dosis_cantidad":"4751","segunda_dosis_cantidad":"4"},{"vacuna_nombre":"Cansino Ad5 nCoV","primera_dosis_cantidad":"1030","segunda_dosis_cantidad":"0"},{"vacuna_nombre":"Moderna ARNm","primera_dosis_cantidad":"6948","segunda_dosis_cantidad":"19722"},{"vacuna_nombre":"Pfizer BioNTech Comirnaty","primera_dosis_cantidad":"2290","segunda_dosis_cantidad":"13"},{"vacuna_nombre":"Sinopharm Vacuna SARSCOV 2 inactivada","primera_dosis_cantidad":"111593","segunda_dosis_cantidad":"83125"},{"vacuna_nombre":"Sputnik V COVID19 Instituto Gamaleya","primera_dosis_cantidad":"93826","segunda_dosis_cantidad":"53104"}]}]
